{
  "episodes": [
    {
      "episodeNumber": "224",
      "title": "Muak Lek to Pak Chong Scenic Route",
      "url": "https://www.youtube.com/watch?v=rQEw6jDxmk8",
      "date": "2024-11-30",
      "time": "10:00 AM",
      "quality": "Full HD 1080p",
      "route": {
        "start": "Muak Lek, Saraburi",
        "via": ["Klang Dong"],
        "end": "Pak Chong, Nakhon Ratchasima",
        "road": "Highway 2 (Mittraphap Road)",
        "type": "scenic"
      },
      "weather": "Clear sky, good visibility",
      "pointsOfInterest": [
        "Muak Lek District views",
        "Mountain landscapes",
        "Klang Dong local area",
        "Pak Chong entrance"
      ],
      "title_en": "Muak Lek - Klang Dong - Pak Chong Scenic Drive | Thailand Dashcam EP.224"
    },
    {
      "episodeNumber": "223",
      "title": "Phahonyothin Road Wang Noi to Saraburi Bypass",
      "url": "https://youtu.be/ISqxo-O7DNA",
      "date": "2024-11-30",
      "time": "09:00 AM",
      "quality": "Full HD 1080p",
      "route": {
        "start": "Phahonyothin Wang Noi",
        "via": ["Saraburi Bypass"],
        "end": "Mittraphap Road, Kaeng Khoi",
        "type": "highway"
      },
      "weather": "Clear Sky",
      "title_en": "Driving from Phahonyothin Road Wang Noi to Saraburi Bypass - Kaeng Khoi, Saraburi"
    },
    {
      "episodeNumber": "222",
      "title": "Phahonyothin Road: Bang Pa-in to Wangnoi",
      "url": "https://www.youtube.com/watch?v=M98qMx27i2s",
      "route": {
        "road": "Phahonyothin Road",
        "start": "Bang Pa-in",
        "end": "Wangnoi",
        "type": "highway"
      },
      "title_en": "Phahonyothin Road: Bang Pa-in to Wangnoi"
    },
    {
      "episodeNumber": "221",
      "title": "Bangkok to Bang Pa-in Expressway Drive",
      "url": "https://youtu.be/K6CYzVHe80Y",
      "date": "2024-11-29",
      "time": "08:30 AM",
      "quality": "Full HD 1080p",
      "route": {
        "start": "Bangkok (Bang Sue)",
        "via": ["Don Mueang Tollway", "Bangpa-in Expressway"],
        "end": "Bang Pa-in, Ayutthaya",
        "type": "highway",
        "distance": "76 km"
      },
      "weather": "Clear sky, good visibility",
      "pointsOfInterest": [
        "Don Mueang International Airport view",
        "Rangsit area",
        "Elevated expressway sections",
        "Bang Pa-in Industrial Estate",
        "Bang Pa-in Junction"
      ],
      "title_en": "Bangkok to Bang Pa-in Expressway Drive | Thailand Dashcam EP.221"
    }
  ],
  "metadata": {
    "lastUpdated": "2024-11-30",
    "totalEpisodes": 4,
    "videoQuality": "Full HD 1080p",
    "regions": [
      "Bangkok",
      "Ayutthaya",
      "Saraburi",
      "Nakhon Ratchasima"
    ]
  }
}