{
  "episodes": [
    {
      "episodeNumber": "224",
      "title": {
        "en": "Muak Lek - Klang Dong - Pak Chong Scenic Drive",
        "th": "นั่งรถเที่ยว มวกเหล็ก-กลางดง-ปากช่อง",
        "zh": "泰国风景路线：Muak Lek-Klang Dong-Pak Chong",
        "ko": "무악렉-클랑동-팍총 드라이브 코스",
        "ja": "ムアクレック-クランドン-パクチョン絶景ドライブ",
        "hi": "मुआक लेक - क्लांग डोंग - पाक चोंग सड़क यात्रा"
      },
      "description": {
        "en": "A scenic drive through Muak Lek - Klang Dong - Pak Chong route, Saraburi-Nakhon Ratchasima Province. Clear weather, open road, light traffic.",
        "th": "ขับรถผ่านเส้นทางธรรมชาติสวยงาม มวกเหล็ก-กลางดง-ปากช่อง จ.สระบุรี-นครราชสีมา สภาพอากาศแจ่มใส ถนนโล่ง การจราจรเบาบาง"
      },
      "date": "2024-11-30",
      "time": "10:00 AM",
      "url": "https://www.youtube.com/watch?v=rQEw6jDxmk8",
      "quality": "Full HD 1080p",
      "route": {
        "start": "Muak Lek, Saraburi",
        "via": ["Klang Dong"],
        "end": "Pak Chong, Nakhon Ratchasima",
        "type": "Scenic Drive",
        "road": "Highway 2 (Mittraphap Road)"
      },
      "weather": "Clear sky, good visibility",
      "roadConditions": "Good, light traffic",
      "pointsOfInterest": [
        "Muak Lek District views",
        "Mountain landscapes",
        "Klang Dong local area",
        "Pak Chong entrance",
        "Highway signage"
      ]
    },
    {
      "episodeNumber": "223",
      "title": {
        "en": "Driving from Phahonyothin Road Wang Noi to Saraburi Bypass - Kaeng Khoi, Saraburi",
        "th": "พหลโยธิน วังน้อย ไปเลี่ยงเมืองสระบุรี ถึงมิตรภาพ แก่งคอย สระบุรี",
        "zh": "从帕荷尤停路旺诺伊到沙拉武里绕城公路 - 桐艾府沙拉武里府",
        "ko": "파홀요틴 도로 왕노이에서 사라부리 우회도로 - 캥코이, 사라부리까지",
        "ja": "パホンヨーティン通りワンノーイからサラブリーバイパス - ケーンコーイ、サラブリーまで",
        "hi": "फाहोन्योथिन रोड वांग नोई से सरबुरी बाईपास - काएंग खोई, सरबुरी तक"
      },
      "date": "2024-11-30",
      "time": "09:00 AM",
      "url": "https://youtu.be/ISqxo-O7DNA",
      "quality": "Full HD 1080p",
      "route": {
        "type": "Highway Drive",
        "waypoints": [
          "ถนนพหลโยธิน วังน้อย",
          "ถนนเลี่ยงเมืองสระบุรี",
          "ถนนมิตรภาพ แก่งคอย สระบุรี"
        ]
      },
      "weather": "Clear Sky"
    },
    {
      "episodeNumber": "222",
      "title": {
        "en": "Phahonyothin Road: Bang Pa-in to Wangnoi",
        "th": "ขับรถเที่ยวไทย EP.222 | ถนนพหลโยธิน บางปะอิน-วังน้อย",
        "zh": "泰国自驾之旅 EP.222 | 帕荷约庭路：邦巴引-旺诺",
        "ko": "태국 드라이브 EP.222 | 파혼요틴 도로: 방파인-왕노이 구간",
        "ja": "タイドライブスルー EP.222 | パホンヨーティン通り：バンパイン-ワンノーイ間"
      },
      "url": "https://www.youtube.com/watch?v=M98qMx27i2s",
      "route": {
        "road": "Phahonyothin Road",
        "start": "Bang Pa-in",
        "end": "Wangnoi"
      }
    }
  ],
  "metadata": {
    "lastUpdated": "2024-11-30",
    "totalEpisodes": 3,
    "availableLanguages": ["en", "th", "zh", "ko", "ja", "hi"],
    "videoQuality": "Full HD 1080p",
    "regions": [
      "Saraburi",
      "Nakhon Ratchasima",
      "Bang Pa-in",
      "Wangnoi"
    ]
  }
}